pyrobogui.py
pyrobogui-0.0.8.dist-info/LICENSE
pyrobogui-0.0.8.dist-info/METADATA
pyrobogui-0.0.8.dist-info/WHEEL
pyrobogui-0.0.8.dist-info/top_level.txt
pyrobogui-0.0.8.dist-info/RECORD
