Metadata-Version: 2.1
Name: pyrobogui
Version: 0.0.8
Summary: Wrapper around pyautogui for automating mouse and keyboard - plus some new functions
Home-page: https://github.com/ClimenteA/pyrobogui
Author: Climente Alin
Author-email: climente.alin@gmail.com
License: MIT
Platform: UNKNOWN
Requires-Dist: pyautogui
Requires-Dist: pyperclip
